kwatch/__init__.py
kwatch-0.0.2.dist-info/LICENSE
kwatch-0.0.2.dist-info/METADATA
kwatch-0.0.2.dist-info/WHEEL
kwatch-0.0.2.dist-info/top_level.txt
kwatch-0.0.2.dist-info/RECORD
