Metadata-Version: 2.1
Name: kwatch
Version: 0.0.2
Summary: Python client for the KWatch.io webhooks
Home-page: https://kwatch.io
Author: Arthur Delerue
Author-email: arthur@kwatch.io
License: MIT
Keywords: webhooks,reddit,twitter,hackernews
License-File: LICENSE
